{"imagePath": "dad/documents/ELS_HS_AMP_2018_V5_3/ELS_HS_AMP_2018_V5_3-1.jpg", "imageData": null, "shapes": [{"shape_type": "rectangle", "points": [[101, 456], [1353, 501]], "flags": {}, "group_id": 41, "label": "title"}, {"shape_type": "rectangle", "points": [[103, 516], [1066, 557]], "flags": {}, "group_id": 11, "label": "author_name"}, {"shape_type": "rectangle", "points": [[102, 571], [1239, 644]], "flags": {}, "group_id": 6, "label": "affiliation"}, {"shape_type": "rectangle", "points": [[555, 710], [1555, 926]], "flags": {}, "group_id": 3, "label": "abstract"}, {"shape_type": "rectangle", "points": [[96, 765], [296, 938]], "flags": {}, "group_id": 30, "label": "keywords"}, {"shape_type": "rectangle", "points": [[101, 1869], [1325, 1950]], "flags": {}, "group_id": 17, "label": "contact_info"}, {"shape_type": "rectangle", "points": [[101, 1970], [519, 1997]], "flags": {}, "group_id": 22, "label": "doi"}, {"shape_type": "rectangle", "points": [[99, 2053], [1193, 2101]], "flags": {}, "group_id": 18, "label": "copyright"}, {"shape_type": "rectangle", "points": [[101, 2003], [1014, 2045]], "flags": {}, "group_id": 8, "label": "article_history"}, {"shape_type": "rectangle", "points": [[727, 232], [935, 281]], "flags": {}, "group_id": 29, "label": "journal"}, {"shape_type": "rectangle", "points": [[701, 97], [805, 121]], "flags": {}, "group_id": 29, "label": "journal"}, {"shape_type": "rectangle", "points": [[827, 98], [887, 121]], "flags": {}, "group_id": 21, "label": "date"}, {"shape_type": "rectangle", "points": [[95, 168], [295, 357]], "flags": {}, "group_id": 35, "label": "publisher"}, {"shape_type": "rectangle", "points": [[101, 1030], [277, 1065]], "flags": {}, "group_id": 38, "label": "section_heading"}, {"shape_type": "rectangle", "points": [[842, 1023], [1554, 1813]], "flags": {}, "group_id": 19, "label": "core_text"}, {"shape_type": "rectangle", "points": [[95, 1081], [807, 1812]], "flags": {}, "group_id": 19, "label": "core_text"}], "version": "4.2.10", "flags": {}, "imageHeight": 2205, "imageWidth": 1654}