{"imagePath": "dad/documents/WIL_HS_APPS_2019_2_4/WIL_HS_APPS_2019_2_4-11.jpg", "imageData": null, "shapes": [{"shape_type": "rectangle", "points": [[90, 378], [1274, 1115]], "flags": {}, "group_id": [19, 19, 19], "label": "core_text"}, {"shape_type": "rectangle", "points": [[93, 106], [1268, 261]], "flags": {}, "group_id": [19, 19, 19], "label": "core_text"}, {"shape_type": "rectangle", "points": [[93, 1156], [234, 1203]], "flags": {}, "group_id": [38, 38, 38], "label": "section_heading"}, {"shape_type": "rectangle", "points": [[89, 1212], [863, 1266]], "flags": {}, "group_id": [17, 17, 17], "label": "contact_info"}, {"shape_type": "rectangle", "points": [[82, 1305], [336, 1352]], "flags": {}, "group_id": [38, 38, 38], "label": "section_heading"}, {"shape_type": "rectangle", "points": [[90, 302], [715, 363]], "flags": {}, "group_id": [38, 38, 38], "label": "section_heading"}, {"shape_type": "rectangle", "points": [[91, 1747], [1234, 1840]], "flags": {}, "group_id": [34, 34, 34], "label": "note"}, {"shape_type": "rectangle", "points": [[85, 1361], [1251, 1729]], "flags": {}, "group_id": [37, 37, 37], "label": "reference"}], "version": "4.2.10", "flags": {}, "imageHeight": 1938, "imageWidth": 1347}