{"imagePath": "dad/documents/SPR_ENG_RED_2015_3_1/SPR_ENG_RED_2015_3_1-1.jpg", "imageData": null, "shapes": [{"shape_type": "rectangle", "points": [[136, 1804], [372, 1853]], "flags": {}, "group_id": [38, 38, 38], "label": "section_heading"}, {"shape_type": "rectangle", "points": [[843, 160], [1519, 2015]], "flags": {}, "group_id": [19, 19, 19], "label": "core_text"}, {"shape_type": "rectangle", "points": [[133, 1879], [810, 2001]], "flags": {}, "group_id": [19, 19, 19], "label": "core_text"}, {"shape_type": "rectangle", "points": [[124, 146], [816, 1752]], "flags": {}, "group_id": [19, 19, 19], "label": "core_text"}], "version": "4.2.10", "flags": {}, "imageHeight": 2197, "imageWidth": 1654}