{"imagePath": "dad/documents/ELS_ENG_RIE_2020_V6_11/ELS_ENG_RIE_2020_V6_11-1.jpg", "imageData": null, "shapes": [{"shape_type": "rectangle", "points": [[81, 452], [1035, 546]], "flags": {}, "group_id": [41, 41, 41], "label": "title"}, {"shape_type": "rectangle", "points": [[81, 562], [1296, 652]], "flags": {}, "group_id": [11, 11, 11], "label": "author_name"}, {"shape_type": "rectangle", "points": [[83, 663], [1080, 757]], "flags": {}, "group_id": [6, 6, 6], "label": "affiliation"}, {"shape_type": "rectangle", "points": [[544, 788], [1569, 1159]], "flags": {}, "group_id": [3, 3, 3], "label": "abstract"}, {"shape_type": "rectangle", "points": [[86, 856], [317, 967]], "flags": {}, "group_id": [30, 30, 30], "label": "keywords"}, {"shape_type": "rectangle", "points": [[110, 1859], [671, 1918]], "flags": {}, "group_id": [17, 17, 17], "label": "contact_info"}, {"shape_type": "rectangle", "points": [[99, 1931], [530, 1963]], "flags": {}, "group_id": [22, 22, 22], "label": "doi"}, {"shape_type": "rectangle", "points": [[92, 1962], [922, 1984]], "flags": {}, "group_id": [8, 8, 8], "label": "article_history"}, {"shape_type": "rectangle", "points": [[93, 1990], [1559, 2038]], "flags": {}, "group_id": [18, 18, 18], "label": "copyright"}, {"shape_type": "rectangle", "points": [[99, 1230], [248, 1270]], "flags": {}, "group_id": [38, 38, 38], "label": "section_heading"}, {"shape_type": "rectangle", "points": [[90, 1294], [815, 1806]], "flags": {}, "group_id": [19, 19, 19], "label": "core_text"}, {"shape_type": "rectangle", "points": [[833, 1224], [1567, 1811]], "flags": {}, "group_id": [19, 19, 19], "label": "core_text"}, {"shape_type": "rectangle", "points": [[866, 93], [931, 123]], "flags": {}, "group_id": [21, 21, 21], "label": "date"}, {"shape_type": "rectangle", "points": [[93, 168], [282, 362]], "flags": {}, "group_id": [35, 35, 35], "label": "publisher"}, {"shape_type": "rectangle", "points": [[629, 227], [1028, 299]], "flags": {}, "group_id": [29, 29, 29], "label": "journal"}], "version": "4.2.10", "flags": {}, "imageHeight": 2205, "imageWidth": 1654}