{"imagePath": "dad/documents/SAG_HS_SO_2019_3_9/SAG_HS_SO_2019_3_9-3.jpg", "imageData": null, "shapes": [{"shape_type": "rectangle", "points": [[880, 565], [1480, 803]], "flags": {}, "group_id": 32, "label": "math_formula"}, {"shape_type": "rectangle", "points": [[925, 832], [1015, 871]], "flags": {}, "group_id": 32, "label": "math_formula"}, {"shape_type": "rectangle", "points": [[1067, 828], [1090, 869]], "flags": {}, "group_id": 32, "label": "math_formula"}, {"shape_type": "rectangle", "points": [[253, 928], [728, 1021]], "flags": {}, "group_id": 32, "label": "math_formula"}, {"shape_type": "rectangle", "points": [[209, 1069], [232, 1104]], "flags": {}, "group_id": 32, "label": "math_formula"}, {"shape_type": "rectangle", "points": [[186, 1105], [216, 1140]], "flags": {}, "group_id": 32, "label": "math_formula"}, {"shape_type": "rectangle", "points": [[496, 1107], [526, 1140]], "flags": {}, "group_id": 32, "label": "math_formula"}, {"shape_type": "rectangle", "points": [[190, 1144], [213, 1172]], "flags": {}, "group_id": 32, "label": "math_formula"}, {"shape_type": "rectangle", "points": [[435, 1138], [469, 1173]], "flags": {}, "group_id": 32, "label": "math_formula"}, {"shape_type": "rectangle", "points": [[707, 1136], [741, 1178]], "flags": {}, "group_id": 32, "label": "math_formula"}, {"shape_type": "rectangle", "points": [[150, 1742], [752, 2042]], "flags": {}, "group_id": 32, "label": "math_formula"}, {"shape_type": "rectangle", "points": [[930, 187], [946, 224]], "flags": {}, "group_id": 32, "label": "math_formula"}, {"shape_type": "rectangle", "points": [[1372, 187], [1396, 231]], "flags": {}, "group_id": 32, "label": "math_formula"}, {"shape_type": "rectangle", "points": [[1024, 230], [1101, 258]], "flags": {}, "group_id": 32, "label": "math_formula"}, {"shape_type": "rectangle", "points": [[1156, 226], [1179, 263]], "flags": {}, "group_id": 32, "label": "math_formula"}, {"shape_type": "rectangle", "points": [[845, 260], [880, 301]], "flags": {}, "group_id": 32, "label": "math_formula"}, {"shape_type": "rectangle", "points": [[1487, 727], [1529, 791]], "flags": {}, "group_id": 28, "label": "index"}, {"shape_type": "rectangle", "points": [[759, 957], [809, 999]], "flags": {}, "group_id": 28, "label": "index"}, {"shape_type": "rectangle", "points": [[759, 1906], [808, 1950]], "flags": {}, "group_id": 28, "label": "index"}, {"shape_type": "rectangle", "points": [[850, 960], [1366, 1005]], "flags": {}, "group_id": 39, "label": "subheading"}, {"shape_type": "rectangle", "points": [[843, 1008], [1020, 1046]], "flags": {}, "group_id": 39, "label": "subheading"}, {"shape_type": "rectangle", "points": [[839, 1230], [1113, 1280]], "flags": {}, "group_id": 39, "label": "subheading"}, {"shape_type": "rectangle", "points": [[843, 1702], [1385, 1739]], "flags": {}, "group_id": 39, "label": "subheading"}, {"shape_type": "rectangle", "points": [[127, 1255], [614, 1294]], "flags": {}, "group_id": 39, "label": "subheading"}, {"shape_type": "rectangle", "points": [[132, 565], [346, 609]], "flags": {}, "group_id": 39, "label": "subheading"}, {"shape_type": "rectangle", "points": [[127, 505], [624, 551]], "flags": {}, "group_id": 38, "label": "section_heading"}, {"shape_type": "rectangle", "points": [[843, 905], [1220, 950]], "flags": {}, "group_id": 38, "label": "section_heading"}, {"shape_type": "rectangle", "points": [[842, 1299], [1543, 1672]], "flags": {}, "group_id": 19, "label": "core_text"}, {"shape_type": "rectangle", "points": [[849, 1755], [1542, 2057]], "flags": {}, "group_id": 19, "label": "core_text"}, {"shape_type": "rectangle", "points": [[87, 1314], [820, 2089]], "flags": {}, "group_id": 19, "label": "core_text"}, {"shape_type": "rectangle", "points": [[85, 613], [836, 1227]], "flags": {}, "group_id": 19, "label": "core_text"}, {"shape_type": "rectangle", "points": [[836, 1051], [1569, 1214]], "flags": {}, "group_id": 19, "label": "core_text"}, {"shape_type": "rectangle", "points": [[843, 150], [1581, 878]], "flags": {}, "group_id": 19, "label": "core_text"}, {"shape_type": "rectangle", "points": [[77, 174], [821, 467]], "flags": {}, "group_id": 19, "label": "core_text"}], "version": "4.2.10", "flags": {}, "imageHeight": 2200, "imageWidth": 1700}