{"imagePath": "dad/documents/WIL_ENG_AS_2020_4_16/WIL_ENG_AS_2020_4_16-0.jpg", "imageData": null, "shapes": [{"shape_type": "rectangle", "points": [[120, 180], [1381, 384]], "flags": {}, "group_id": [41, 41, 41], "label": "title"}, {"shape_type": "rectangle", "points": [[120, 406], [1455, 521]], "flags": {}, "group_id": [11, 11, 11], "label": "author_name"}, {"shape_type": "rectangle", "points": [[126, 602], [1020, 1093]], "flags": {}, "group_id": [3, 3, 3], "label": "abstract"}, {"shape_type": "rectangle", "points": [[122, 1162], [816, 1764]], "flags": {}, "group_id": [6, 6, 6], "label": "affiliation"}, {"shape_type": "rectangle", "points": [[122, 1771], [823, 1829]], "flags": {}, "group_id": [17, 17, 17], "label": "contact_info"}, {"shape_type": "rectangle", "points": [[120, 1841], [819, 1945]], "flags": {}, "group_id": [18, 18, 18], "label": "copyright"}, {"shape_type": "rectangle", "points": [[115, 1960], [467, 2000]], "flags": {}, "group_id": [22, 22, 22], "label": "doi"}, {"shape_type": "rectangle", "points": [[210, 2052], [253, 2085]], "flags": {}, "group_id": [21, 21, 21], "label": "date"}, {"shape_type": "rectangle", "points": [[841, 1143], [1530, 2013]], "flags": {}, "group_id": [19, 19, 19], "label": "core_text"}, {"shape_type": "rectangle", "points": [[1059, 646], [1531, 1139]], "flags": {}, "group_id": [19, 19, 19], "label": "core_text"}, {"shape_type": "rectangle", "points": [[1055, 577], [1294, 623]], "flags": {}, "group_id": [38, 38, 38], "label": "section_heading"}, {"shape_type": "rectangle", "points": [[135, 2056], [207, 2084]], "flags": {}, "group_id": [29, 29, 29], "label": "journal"}, {"shape_type": "rectangle", "points": [[1304, 30], [1510, 115]], "flags": {}, "group_id": [29, 29, 29], "label": "journal"}, {"shape_type": "rectangle", "points": [[1112, 2051], [1528, 2087]], "flags": {}, "group_id": [35, 35, 35], "label": "publisher"}], "version": "4.2.10", "flags": {}, "imageHeight": 2174, "imageWidth": 1654}